main.py
cf_polygon_mcp-0.3.2.dist-info/licenses/LICENSE
src/__init__.py
src/mcp/__init__.py
src/mcp/server.py
src/mcp/utils/__init__.py
src/mcp/utils/common.py
src/mcp/utils/contest_problems.py
src/mcp/utils/problem_checker.py
src/mcp/utils/problem_file.py
src/mcp/utils/problem_info.py
src/mcp/utils/problem_interactor.py
src/mcp/utils/problem_save_statement.py
src/mcp/utils/problem_solution_view.py
src/mcp/utils/problem_solutions.py
src/mcp/utils/problem_statements.py
src/mcp/utils/problem_update_info.py
src/mcp/utils/problem_validator.py
src/mcp/utils/problem_working_copy.py
src/mcp/utils/problems.py
src/polygon/__init__.py
src/polygon/client.py
src/polygon/contest.py
src/polygon/models.py
src/polygon/problem.py
src/polygon/api/__init__.py
src/polygon/api/contest_problems.py
src/polygon/api/problem_checker.py
src/polygon/api/problem_discard_working_copy.py
src/polygon/api/problem_info.py
src/polygon/api/problem_interactor.py
src/polygon/api/problem_save_statement.py
src/polygon/api/problem_solutions.py
src/polygon/api/problem_statements.py
src/polygon/api/problem_update_info.py
src/polygon/api/problem_update_working_copy.py
src/polygon/api/problem_validator.py
src/polygon/api/problem_view_file.py
src/polygon/api/problem_view_solution.py
src/polygon/api/problems.py
src/polygon/utils/__init__.py
src/polygon/utils/client_utils.py
src/polygon/utils/contest_utils.py
src/polygon/utils/problem_utils.py
cf_polygon_mcp-0.3.2.dist-info/METADATA
cf_polygon_mcp-0.3.2.dist-info/WHEEL
cf_polygon_mcp-0.3.2.dist-info/entry_points.txt
cf_polygon_mcp-0.3.2.dist-info/top_level.txt
cf_polygon_mcp-0.3.2.dist-info/RECORD
