Metadata-Version: 2.4
Name: cf-polygon-mcp
Version: 0.3.2
Summary: 基于 Codeforces Polygon API 的 MCP 工具集
Requires-Python: >=3.13
License-File: LICENSE
Requires-Dist: mcp[cli]>=1.6.0
Requires-Dist: requests>=2.32.3
Dynamic: license-file
